pytest_argus_reporter.py
pytest_argus_reporter-0.15.7.dist-info/licenses/LICENSE
pytest_argus_reporter-0.15.7.dist-info/METADATA
pytest_argus_reporter-0.15.7.dist-info/WHEEL
pytest_argus_reporter-0.15.7.dist-info/entry_points.txt
pytest_argus_reporter-0.15.7.dist-info/top_level.txt
pytest_argus_reporter-0.15.7.dist-info/RECORD
