Metadata-Version: 2.4
Name: pytest-argus-reporter
Version: 0.15.7
Summary: A simple plugin to report results of test into argus
Author-email: Scylladb <qa@scylladb.com>
License-Expression: Apache-2.0
Keywords: pytest,testing
Classifier: Development Status :: 4 - Beta
Classifier: Framework :: Pytest
Classifier: Intended Audience :: Developers
Classifier: Topic :: Software Development :: Testing
Classifier: Programming Language :: Python
Classifier: Programming Language :: Python :: 3
Classifier: Programming Language :: Python :: 3.10
Classifier: Programming Language :: Python :: 3.11
Classifier: Programming Language :: Python :: 3.12
Classifier: Programming Language :: Python :: 3.13
Classifier: Operating System :: OS Independent
Requires-Python: >=3.10
License-File: LICENSE
Requires-Dist: argus-alm
Requires-Dist: six>=1.10.0
Provides-Extra: dev
Requires-Dist: pytest~=9.0.0; extra == "dev"
Requires-Dist: pre-commit; extra == "dev"
Requires-Dist: requests-mock; extra == "dev"
Requires-Dist: codecov; extra == "dev"
Requires-Dist: pytest-cov; extra == "dev"
Requires-Dist: nox; extra == "dev"
Requires-Dist: pytest-xdist; extra == "dev"
Requires-Dist: ruff; extra == "dev"
Requires-Dist: autopep8; extra == "dev"
Dynamic: license-file
